analogous/__init__.py
analogous-0.0.1.dist-info/METADATA
analogous-0.0.1.dist-info/WHEEL
analogous-0.0.1.dist-info/RECORD
