Metadata-Version: 2.1
Name: analogous
Version: 0.0.1
Summary: An organizational concepts framework
License: Apache 2.0
Author: RenChu Wang
Author-email: patrick1031wang@gmail.com
Requires-Python: >=3.10,<4.0
Classifier: License :: Other/Proprietary License
Classifier: Programming Language :: Python :: 3
Classifier: Programming Language :: Python :: 3.10
Classifier: Programming Language :: Python :: 3.11
